{
  "svg_viewbox": [
    0,
    0,
    14400.0,
    8964.66
  ],
  "png_size": [
    4000,
    2491
  ],
  "assignments": [
    {
      "indices": [
        6
      ],
      "letter": "A",
      "variant": "alt",
      "glyph_name": "A.alt",
      "conf": 93.0,
      "bbox": [
        665.6214221050087,
        1314.4353881244292,
        1934.328125,
        2650.7306135729664
      ]
    },
    {
      "indices": [
        7
      ],
      "letter": "A",
      "variant": "base",
      "glyph_name": "A",
      "conf": 96.0,
      "bbox": [
        665.6214221050087,
        1314.436154037627,
        925.3125,
        1641.7148440000008
      ]
    },
    {
      "indices": [
        23
      ],
      "letter": "B",
      "variant": "alt",
      "glyph_name": "B.alt",
      "conf": -1.0,
      "bbox": [
        1636.488281,
        2179.375,
        1934.335938,
        2650.722656
      ]
    },
    {
      "indices": [
        19
      ],
      "letter": "B",
      "variant": "base",
      "glyph_name": "B",
      "conf": -1.0,
      "bbox": [
        1477.320312,
        2022.8203120000005,
        925.316406,
        1641.707031
      ]
    },
    {
      "indices": [
        2
      ],
      "letter": "C",
      "variant": "base",
      "glyph_name": "C",
      "conf": 89.0,
      "bbox": [
        2186.125,
        2834.102877942283,
        911.0273439999997,
        1656.0
      ]
    },
    {
      "indices": [
        35
      ],
      "letter": "D",
      "variant": "base",
      "glyph_name": "D",
      "conf": 29.0,
      "bbox": [
        2976.558594,
        3563.7539060000017,
        925.316406,
        1641.707031
      ]
    },
    {
      "indices": [
        8
      ],
      "letter": "E",
      "variant": "alt",
      "glyph_name": "E.alt",
      "conf": 38.0,
      "bbox": [
        3810.90625,
        4281.879647823807,
        1879.785156,
        2596.171875
      ]
    },
    {
      "indices": [
        21
      ],
      "letter": "E",
      "variant": "base",
      "glyph_name": "E",
      "conf": 84.0,
      "bbox": [
        3794.7109379999984,
        4265.684427665888,
        925.316406,
        1641.707031
      ]
    },
    {
      "indices": [
        9
      ],
      "letter": "F",
      "variant": "alt",
      "glyph_name": "F.alt",
      "conf": -1.0,
      "bbox": [
        4468.351561999998,
        4927.91489569128,
        1879.785156,
        2596.172708667841
      ]
    },
    {
      "indices": [
        22
      ],
      "letter": "F",
      "variant": "base",
      "glyph_name": "F",
      "conf": -1.0,
      "bbox": [
        4560.457031,
        5020.020456672876,
        925.3203119999997,
        1641.707031
      ]
    },
    {
      "indices": [
        34
      ],
      "letter": "G",
      "variant": "base",
      "glyph_name": "G",
      "conf": -1.0,
      "bbox": [
        5231.949219,
        5868.613281000002,
        911.0273439999997,
        1656.0
      ]
    },
    {
      "indices": [
        11
      ],
      "letter": "H",
      "variant": "base",
      "glyph_name": "H",
      "conf": 0.0,
      "bbox": [
        6022.222656,
        6598.429688,
        925.316406,
        1641.707031
      ]
    },
    {
      "indices": [
        20
      ],
      "letter": "I",
      "variant": "base",
      "glyph_name": "I",
      "conf": -1.0,
      "bbox": [
        7015.367188,
        7125.363281,
        925.316406,
        1641.707031
      ]
    },
    {
      "indices": [
        16
      ],
      "letter": "J",
      "variant": "base",
      "glyph_name": "J",
      "conf": 94.0,
      "bbox": [
        7596.665934438041,
        8064.152344000002,
        918.171875,
        1648.851562
      ]
    },
    {
      "indices": [
        15
      ],
      "letter": "K",
      "variant": "alt",
      "glyph_name": "K.alt",
      "conf": 91.0,
      "bbox": [
        8322.085937999998,
        8858.819729734987,
        1872.020989170832,
        2603.664062
      ]
    },
    {
      "indices": [
        14
      ],
      "letter": "K",
      "variant": "base",
      "glyph_name": "K",
      "conf": 86.0,
      "bbox": [
        8326.957030999994,
        8853.947061559144,
        925.3117196773294,
        1641.7109380000006
      ]
    },
    {
      "indices": [
        13
      ],
      "letter": "L",
      "variant": "base",
      "glyph_name": "L",
      "conf": 90.0,
      "bbox": [
        9113.273438,
        9587.715676933207,
        925.316406,
        1641.707031
      ]
    },
    {
      "indices": [
        17
      ],
      "letter": "M",
      "variant": "alt",
      "glyph_name": "M.alt",
      "conf": 91.0,
      "bbox": [
        9769.664062,
        10451.40625,
        1877.7868469177224,
        2594.1767066728744
      ]
    },
    {
      "indices": [
        36
      ],
      "letter": "M",
      "variant": "alt2",
      "glyph_name": "M.alt2",
      "conf": -1.0,
      "bbox": [
        9589.499999999995,
        10631.570312000005,
        2805.652344,
        3494.414062
      ]
    },
    {
      "indices": [
        18
      ],
      "letter": "M",
      "variant": "base",
      "glyph_name": "M",
      "conf": 90.0,
      "bbox": [
        9754.550780999994,
        10466.520045811241,
        924.1192973910847,
        1642.907083667841
      ]
    },
    {
      "indices": [
        12
      ],
      "letter": "N",
      "variant": "base",
      "glyph_name": "N",
      "conf": 89.0,
      "bbox": [
        10588.46875,
        11152.691406000005,
        925.3159155876571,
        1641.710938
      ]
    },
    {
      "indices": [
        39
      ],
      "letter": "O",
      "variant": "alt",
      "glyph_name": "O.alt",
      "conf": -1.0,
      "bbox": [
        11306.632812,
        12031.972656,
        1864.757811999999,
        2590.101562
      ]
    },
    {
      "indices": [
        1
      ],
      "letter": "O",
      "variant": "base",
      "glyph_name": "O",
      "conf": 92.0,
      "bbox": [
        11293.632812,
        11967.609375000013,
        911.0273439999997,
        1656.0
      ]
    },
    {
      "indices": [
        29
      ],
      "letter": "P",
      "variant": "alt",
      "glyph_name": "P.alt",
      "conf": -1.0,
      "bbox": [
        12108.550781,
        12638.378906,
        1879.671875,
        2597.257812
      ]
    },
    {
      "indices": [
        30
      ],
      "letter": "P",
      "variant": "base",
      "glyph_name": "P",
      "conf": -1.0,
      "bbox": [
        12128.25,
        12653.074219,
        924.7226559999997,
        1642.3046880000006
      ]
    },
    {
      "indices": [
        25
      ],
      "letter": "Q",
      "variant": "alt",
      "glyph_name": "Q.alt",
      "conf": 93.0,
      "bbox": [
        12799.996094,
        13501.415877248011,
        1863.964844,
        2692.710938
      ]
    },
    {
      "indices": [
        5
      ],
      "letter": "Q",
      "variant": "base",
      "glyph_name": "Q",
      "conf": 92.0,
      "bbox": [
        12813.718749999995,
        13487.691406,
        926.1718749999994,
        1782.78125
      ]
    },
    {
      "indices": [
        3
      ],
      "letter": "R",
      "variant": "alt",
      "glyph_name": "R.alt",
      "conf": -1.0,
      "bbox": [
        709.011719,
        1253.0651678048741,
        4842.687499999998,
        5559.082031
      ]
    },
    {
      "indices": [
        4
      ],
      "letter": "R",
      "variant": "base",
      "glyph_name": "R",
      "conf": 70.0,
      "bbox": [
        709.011719,
        1253.059074541852,
        3929.617188,
        4646.0047396912805
      ]
    },
    {
      "indices": [
        24
      ],
      "letter": "S",
      "variant": "base",
      "glyph_name": "S",
      "conf": 91.0,
      "bbox": [
        1488.8073607695937,
        2008.207031,
        3914.410156,
        4661.210938
      ]
    },
    {
      "indices": [
        10
      ],
      "letter": "T",
      "variant": "base",
      "glyph_name": "T",
      "conf": 90.0,
      "bbox": [
        2223.558594,
        2808.394531,
        3929.617188,
        4646.003906
      ]
    },
    {
      "indices": [
        0
      ],
      "letter": "U",
      "variant": "base",
      "glyph_name": "U",
      "conf": 91.0,
      "bbox": [
        2987.78125,
        3579.113281,
        3922.230469,
        4653.390625
      ]
    },
    {
      "indices": [
        37,
        38
      ],
      "letter": "V",
      "variant": "alt",
      "glyph_name": "V.alt",
      "conf": 80.0,
      "bbox": [
        3717.167139104293,
        4438.739110012855,
        4924.988281,
        5641.378906
      ]
    },
    {
      "indices": [
        26
      ],
      "letter": "V",
      "variant": "base",
      "glyph_name": "V",
      "conf": 84.0,
      "bbox": [
        3738.103295168524,
        4363.732157105669,
        3929.6081385826055,
        4646.011719000002
      ]
    },
    {
      "indices": [
        28
      ],
      "letter": "W",
      "variant": "alt",
      "glyph_name": "W.alt",
      "conf": 91.0,
      "bbox": [
        4573.42665533251,
        5461.366530051487,
        4927.514896680659,
        5638.851562
      ]
    },
    {
      "indices": [
        27
      ],
      "letter": "W",
      "variant": "base",
      "glyph_name": "W",
      "conf": 87.0,
      "bbox": [
        4592.604584921683,
        5480.5436207942175,
        3931.6360811178256,
        4643.984375
      ]
    },
    {
      "indices": [
        31
      ],
      "letter": "X",
      "variant": "base",
      "glyph_name": "X",
      "conf": -1.0,
      "bbox": [
        5718.161052701808,
        6298.682652918404,
        3928.8027624495107,
        4646.820312
      ]
    },
    {
      "indices": [
        32
      ],
      "letter": "Y",
      "variant": "base",
      "glyph_name": "Y",
      "conf": 87.0,
      "bbox": [
        6502.788361352957,
        7048.9976283797305,
        3929.6125803205036,
        4646.00864569128
      ]
    },
    {
      "indices": [
        33
      ],
      "letter": "Z",
      "variant": "base",
      "glyph_name": "Z",
      "conf": 91.0,
      "bbox": [
        7256.31815707226,
        7830.408405524481,
        3930.339844,
        4645.281250000002
      ]
    }
  ],
  "ocr": {
    "0": {
      "index": 0,
      "ocr": "U",
      "conf": 91.0
    },
    "1": {
      "index": 1,
      "ocr": "O",
      "conf": 92.0
    },
    "2": {
      "index": 2,
      "ocr": "C",
      "conf": 89.0
    },
    "3": {
      "index": 3,
      "ocr": "R",
      "conf": -1.0
    },
    "4": {
      "index": 4,
      "ocr": "R",
      "conf": 70.0
    },
    "5": {
      "index": 5,
      "ocr": "Q",
      "conf": 92.0
    },
    "6": {
      "index": 6,
      "ocr": "A",
      "conf": 93.0
    },
    "7": {
      "index": 7,
      "ocr": "A",
      "conf": 96.0
    },
    "8": {
      "index": 8,
      "ocr": "E",
      "conf": 38.0
    },
    "9": {
      "index": 9,
      "ocr": "F",
      "conf": -1.0
    },
    "10": {
      "index": 10,
      "ocr": "T",
      "conf": 90.0
    },
    "11": {
      "index": 11,
      "ocr": "H",
      "conf": 0.0
    },
    "12": {
      "index": 12,
      "ocr": "N",
      "conf": 89.0
    },
    "13": {
      "index": 13,
      "ocr": "L",
      "conf": 90.0
    },
    "14": {
      "index": 14,
      "ocr": "K",
      "conf": 86.0
    },
    "15": {
      "index": 15,
      "ocr": "K",
      "conf": 91.0
    },
    "16": {
      "index": 16,
      "ocr": "J",
      "conf": 94.0
    },
    "17": {
      "index": 17,
      "ocr": "M",
      "conf": 91.0
    },
    "18": {
      "index": 18,
      "ocr": "M",
      "conf": 90.0
    },
    "19": {
      "index": 19,
      "ocr": "",
      "conf": -1.0
    },
    "20": {
      "index": 20,
      "ocr": "",
      "conf": -1.0
    },
    "21": {
      "index": 21,
      "ocr": "E",
      "conf": 84.0
    },
    "22": {
      "index": 22,
      "ocr": "F",
      "conf": -1.0
    },
    "23": {
      "index": 23,
      "ocr": "B",
      "conf": -1.0
    },
    "24": {
      "index": 24,
      "ocr": "S",
      "conf": 91.0
    },
    "25": {
      "index": 25,
      "ocr": "Q",
      "conf": 93.0
    },
    "26": {
      "index": 26,
      "ocr": "V",
      "conf": 84.0
    },
    "27": {
      "index": 27,
      "ocr": "W",
      "conf": 87.0
    },
    "28": {
      "index": 28,
      "ocr": "W",
      "conf": 91.0
    },
    "29": {
      "index": 29,
      "ocr": "P",
      "conf": -1.0
    },
    "30": {
      "index": 30,
      "ocr": "P",
      "conf": -1.0
    },
    "31": {
      "index": 31,
      "ocr": "X",
      "conf": -1.0
    },
    "32": {
      "index": 32,
      "ocr": "Y",
      "conf": 87.0
    },
    "33": {
      "index": 33,
      "ocr": "Z",
      "conf": 91.0
    },
    "34": {
      "index": 34,
      "ocr": "G",
      "conf": -1.0
    },
    "35": {
      "index": 35,
      "ocr": "D",
      "conf": 29.0
    },
    "36": {
      "index": 36,
      "ocr": "",
      "conf": -1.0
    },
    "37": {
      "index": 37,
      "ocr": "L",
      "conf": 0.0
    },
    "38": {
      "index": 38,
      "ocr": "Y",
      "conf": 80.0
    },
    "39": {
      "index": 39,
      "ocr": "O",
      "conf": -1.0
    }
  }
}